{
  "$schema": "http://json.schemastore.org/template",
  "author": "FkThat",
  "classifications": [ "FkThat" ],
  "identity": "FkThat.Templates",
  "name": "FkThat Solution",
  "shortName": "ft-sln",
  "tags": { "language": "C#", "type": "project" },
  "sourceName": "FkThat.Templates",
  "sources": [{
    "include": [
      "src/**/*",
      "test/**/*",
      ".editorconfig",
      ".gitignore",
      "Directory.Build.props",
      "FkThat.Templates.sln",
      "global.json",
      "LICENSE",
      "README.md",
      "RELEASE-NOTES"
    ]
  }]
}
